{
  "TranslationProperties": {
    "Name": "items.BoostToken_Taming_Personal_Grand.name",
    "Description": "items.BoostToken_Taming_Personal_Grand.description"
  },
  "Quality": "Epic",
  "Icon": "Icons/ItemsGenerated/Potion_Large.png",
  "Model": "Items/Consumables/XpTokens/Potion_Large.blockymodel",
  "Texture": "Items/Consumables/XpTokens/Green.png",
  "Interactions": {
    "Secondary": {
      "Interactions": [
        {
          "Type": "Charging",
          "FailOnDamage": true,
          "HorizontalSpeedMultiplier": 0.5,
          "Next": {
            "1.0": {
              "Type": "mmo_xp_token_consume"
            }
          }
        }
      ]
    }
  },
  "Tags": {
    "Type": [
      "Consumable"
    ],
    "Family": [
      "XpToken"
    ]
  }
}